.gitignore
LICENSE
README.md
README.rst
setup.py
tox.ini
hamsclientfork/__init__.py
hamsclientfork/__main__.py
hamsclientfork/client.py
hamsclientfork/py.typed
hamsclientfork.egg-info/PKG-INFO
hamsclientfork.egg-info/SOURCES.txt
hamsclientfork.egg-info/dependency_links.txt
hamsclientfork.egg-info/requires.txt
hamsclientfork.egg-info/top_level.txt