Metadata-Version: 2.1
Name: hamsclientfork
Version: 0.2.19
Summary: Library to get data from meteo swiss
Home-page: https://github.com/Rudd-O/hamsclientfork
Author: websylv
Author-email: div@webhu.org
License: MIT
Classifier: Development Status :: 2 - Pre-Alpha
Classifier: License :: OSI Approved :: MIT License
Classifier: Programming Language :: Python :: 3.6
Classifier: Programming Language :: Python :: 3.7
Classifier: Programming Language :: Python :: 3.8
Classifier: Programming Language :: Python :: 3.9
Classifier: Programming Language :: Python :: 3.10
Classifier: Programming Language :: Python :: 3.11
License-File: LICENSE
Requires-Dist: requests>=2.22.0
Requires-Dist: beautifulsoup4>=4.8.2
Requires-Dist: geopy>=2.0.0
